gitmaid/__init__.py
gitmaid/cli.py
gitmaid-0.1.0.dist-info/LICENSE
gitmaid-0.1.0.dist-info/METADATA
gitmaid-0.1.0.dist-info/WHEEL
gitmaid-0.1.0.dist-info/entry_points.txt
gitmaid-0.1.0.dist-info/RECORD
